etools_offline/__init__.py
etools_offline/fields.py
etools_offline/models.py
etools_offline/permissions.py
etools_offline/serializers.py
etools_offline/tasks.py
etools_offline/utils.py
etools_offline/validators.py
etools_offline-0.1.0.dist-info/LICENSE
etools_offline-0.1.0.dist-info/METADATA
etools_offline-0.1.0.dist-info/WHEEL
etools_offline-0.1.0.dist-info/top_level.txt
etools_offline-0.1.0.dist-info/RECORD
