Metadata-Version: 2.1
Name: etools-offline
Version: 0.1.0
Summary: eTools Offline Collect application
Home-page: https://github.com/unicef/etools-offline-collect
Author: UNICEF
Author-email: dev@unicef.org
License: UNICEF
Platform: linux
Classifier: Environment :: Web Environment
Classifier: Programming Language :: Python :: 3.8
Classifier: Framework :: Django
Classifier: Framework :: Django :: 2.2
Classifier: Framework :: Django :: 3.0
Classifier: Intended Audience :: Developers
Requires-Dist: djangorestframework
Requires-Dist: django
Requires-Dist: requests
Requires-Dist: unicef-attachments
Provides-Extra: test
Requires-Dist: django-celery ; extra == 'test'
Requires-Dist: coverage ; extra == 'test'
Requires-Dist: factory-boy ; extra == 'test'
Requires-Dist: faker ; extra == 'test'
Requires-Dist: flake8 ; extra == 'test'
Requires-Dist: isort ; extra == 'test'
Requires-Dist: pytest ; extra == 'test'
Requires-Dist: pytest-cov ; extra == 'test'
Requires-Dist: pytest-django ; extra == 'test'
Requires-Dist: pytest-echo ; extra == 'test'
Requires-Dist: pytest-pythonpath ; extra == 'test'
Requires-Dist: psycopg2-binary ; extra == 'test'
Requires-Dist: responses ; extra == 'test'
